discord_slash/__init__.py
discord_slash/client.py
discord_slash/cog_ext.py
discord_slash/const.py
discord_slash/context.py
discord_slash/dpy_overrides.py
discord_slash/error.py
discord_slash/http.py
discord_slash/model.py
discord_slash/utils/__init__.py
discord_slash/utils/manage_commands.py
discord_slash/utils/manage_components.py
discord_py_slash_command-3.0.3.dist-info/LICENSE
discord_py_slash_command-3.0.3.dist-info/METADATA
discord_py_slash_command-3.0.3.dist-info/WHEEL
discord_py_slash_command-3.0.3.dist-info/top_level.txt
discord_py_slash_command-3.0.3.dist-info/RECORD
