Metadata-Version: 2.1
Name: discord-py-slash-command
Version: 3.0.3
Summary: A slash command handler for discord.py.
Home-page: https://github.com/goverfl0w/discord-interactions
Author: goverfl0w
Author-email: jwalston2002@gmail.com
License: MIT License
Platform: UNKNOWN
Classifier: Development Status :: 4 - Beta
Classifier: Intended Audience :: Developers
Classifier: License :: OSI Approved :: MIT License
Classifier: Natural Language :: English
Classifier: Operating System :: OS Independent
Classifier: Programming Language :: Python :: 3
Classifier: Programming Language :: Python :: 3.6
Classifier: Programming Language :: Python :: 3.7
Classifier: Programming Language :: Python :: 3.8
Classifier: Programming Language :: Python :: 3.9
Classifier: Topic :: Internet
Classifier: Topic :: Software Development :: Libraries :: Python Modules
Classifier: Topic :: Software Development :: Libraries
Classifier: Topic :: Utilities
Requires-Python: >=3.6
Provides-Extra: lint
Provides-Extra: readthedocs
Provides-Extra: dev
License-File: LICENSE
